{
	"configurations" : 
	[
		{
			"directories" : 
			[
				{
					"build" : ".",
					"hasInstallRule" : true,
					"jsonFile" : "directory-.-da5ee73eb1d8f2f331b4.json",
					"minimumCMakeVersion" : 
					{
						"string" : "3.12"
					},
					"projectIndex" : 0,
					"source" : ".",
					"targetIndexes" : 
					[
						0,
						1,
						2,
						3,
						4,
						5
					]
				}
			],
			"name" : "",
			"projects" : 
			[
				{
					"directoryIndexes" : 
					[
						0
					],
					"name" : "bumperbot_controller",
					"targetIndexes" : 
					[
						0,
						1,
						2,
						3,
						4,
						5
					]
				}
			],
			"targets" : 
			[
				{
					"directoryIndex" : 0,
					"id" : "ament_cmake_python_build_bumperbot_controller_egg::@6890427a1f51a3e7e1df",
					"jsonFile" : "target-ament_cmake_python_build_bumperbot_controller_egg-d065b1b6c5e8226b2ee2.json",
					"name" : "ament_cmake_python_build_bumperbot_controller_egg",
					"projectIndex" : 0
				},
				{
					"directoryIndex" : 0,
					"id" : "ament_cmake_python_symlink_bumperbot_controller::@6890427a1f51a3e7e1df",
					"jsonFile" : "target-ament_cmake_python_symlink_bumperbot_controller-f966b915ef052f6b42f0.json",
					"name" : "ament_cmake_python_symlink_bumperbot_controller",
					"projectIndex" : 0
				},
				{
					"directoryIndex" : 0,
					"id" : "bumperbot_controller_uninstall::@6890427a1f51a3e7e1df",
					"jsonFile" : "target-bumperbot_controller_uninstall-8967b97e7909ba5a7f7f.json",
					"name" : "bumperbot_controller_uninstall",
					"projectIndex" : 0
				},
				{
					"directoryIndex" : 0,
					"id" : "noisy_controller::@6890427a1f51a3e7e1df",
					"jsonFile" : "target-noisy_controller-a0d4d0dc75495364d00e.json",
					"name" : "noisy_controller",
					"projectIndex" : 0
				},
				{
					"directoryIndex" : 0,
					"id" : "simple_controller::@6890427a1f51a3e7e1df",
					"jsonFile" : "target-simple_controller-d91b7ae4dfb2a61dfbbd.json",
					"name" : "simple_controller",
					"projectIndex" : 0
				},
				{
					"directoryIndex" : 0,
					"id" : "uninstall::@6890427a1f51a3e7e1df",
					"jsonFile" : "target-uninstall-88132f1e8c5385d804ad.json",
					"name" : "uninstall",
					"projectIndex" : 0
				}
			]
		}
	],
	"kind" : "codemodel",
	"paths" : 
	{
		"build" : "/home/ilhan/bumperbot_ws/build/bumperbot_controller",
		"source" : "/home/ilhan/bumperbot_ws/src/bumperbot_controller"
	},
	"version" : 
	{
		"major" : 2,
		"minor" : 3
	}
}
